{
  "swagger": "2.0",
  "info": {
    "description": "",
    "title": "Account API",
    "contact": {
      "name": "mars"
    },
    "version": "v1"
  },
  "basePath": "/api/v1/accounts",
  "schemes": [
    "http",
    "https"
  ],
  "consumes": [
    "application/json"
  ],
  "produces": [
    "application/json"
  ],
  "securityDefinitions": {
    "Bearer": {
      "type": "apiKey",
      "name": "Authorization",
      "in": "header"
    }
  },
  "parameters": {
  },
  "paths": {
    "/sendLoginSmsCode": {
      "post": {
        "summary": "",
        "operationId": "SendLoginSmsCode",
        "parameters": [
          {
            "in": "query",
            "name": "phone",
            "type": "string",
            "required": true
          },
          {
            "in": "query",
            "name": "captchaId",
            "type": "string",
            "required": true
          },
          {
            "in": "query",
            "name": "captchaCode",
            "type": "string",
            "required": true
          }
        ],
        "responses": {
          "200": {
            "description": "ok"
          }
        }
      }
    },
    "/sendSmsCode": {
      "post": {
        "summary": "",
        "operationId": "SendSmsCode",
        "parameters": [
          {
            "in": "query",
            "name": "scene",
            "type": "string",
            "required": true
          },
          {
            "in": "query",
            "name": "phone",
            "type": "string",
            "required": true
          },
          {
            "in": "query",
            "name": "captchaId",
            "type": "string",
            "required": true
          },
          {
            "in": "query",
            "name": "captchaCode",
            "type": "string",
            "required": true
          }
        ],
        "security": [
          {
            "Bearer": [
            ]
          }
        ],
        "responses": {
          "200": {
            "description": "ok"
          }
        }
      }
    },
    "/smsLogin": {
      "post": {
        "summary": "sms login",
        "operationId": "SmsLogin",
        "parameters": [
          {
            "in": "query",
            "name": "phone",
            "type": "string",
            "required": true
          },
          {
            "in": "query",
            "name": "smsCode",
            "type": "string",
            "required": true
          }
        ],
        "responses": {
          "200": {
            "description": "",
            "schema": {
              "$ref": "#/definitions/userToken"
            }
          }
        }
      }
    },
    "/logout": {
      "post": {
        "summary": "",
        "operationId": "Logout",
        "parameters": [
          {
            "in": "query",
            "name": "accessToken",
            "type": "string",
            "required": true
          },
          {
            "in": "query",
            "name": "refreshToken",
            "type": "string",
            "required": true
          }
        ],
        "responses": {
          "200": {
            "description": "ok"
          }
        }
      }
    },
    "/refreshToken": {
      "post": {
        "summary": "",
        "operationId": "RefreshToken",
        "parameters": [
          {
            "in": "query",
            "name": "refreshToken",
            "type": "string",
            "required": true
          }
        ],
        "responses": {
          "200": {
            "description": "ok",
            "schema": {
              "$ref": "#/definitions/userToken"
            }
          }
        }
      }
    },
    "/oauthState": {
      "post": {
        "summary": "",
        "operationId": "OauthState",
        "parameters": [
        ],
        "responses": {
          "200": {
            "description": "state",
            "schema": {
              "type": "string"
            }
          }
        }
      }
    },
    "/oauthJump": {
      "post": {
        "summary": "",
        "operationId": "OauthJump",
        "parameters": [
          {
            "in": "query",
            "name": "redirectUri",
            "type": "string",
            "required": true
          },
          {
            "in": "query",
            "name": "authorizationCode",
            "type": "string",
            "required": true
          },
          {
            "in": "query",
            "name": "state",
            "type": "string",
            "required": true
          }
        ],
        "responses": {
          "200": {
            "description": "ok",
            "schema": {
              "$ref": "#/definitions/userToken"
            }
          }
        }
      }
    },
    "/userInfo": {
      "get": {
        "summary": "",
        "operationId": "GetUserInfo",
        "parameters": [
        ],
        "security": [
          {
            "Bearer": [
            ]
          }
        ],
        "responses": {
          "200": {
            "description": "",
            "schema": {
              "$ref": "#/definitions/userInfo"
            }
          }
        }
      }
    },
    "/setUserName": {
      "post": {
        "summary": "",
        "operationId": "SetUserName",
        "parameters": [
          {
            "in": "query",
            "name": "userName",
            "type": "string",
            "required": true
          }
        ],
        "security": [
          {
            "Bearer": [
            ]
          }
        ],
        "responses": {
          "200": {
            "description": "ok"
          }
        }
      }
    },
    "/setUserIcon": {
      "post": {
        "summary": "",
        "operationId": "SetUserIcon",
        "parameters": [
          {
            "in": "query",
            "name": "userIcon",
            "type": "string",
            "required": true
          }
        ],
        "security": [
          {
            "Bearer": [
            ]
          }
        ],
        "responses": {
          "200": {
            "description": "ok"
          }
        }
      }
    },
    "/accountInfo": {
      "get": {
        "summary": "",
        "operationId": "GetAccountInfo",
        "parameters": [
        ],
        "security": [
          {
            "Bearer": [
            ]
          }
        ],
        "responses": {
          "200": {
            "description": "",
            "schema": {
              "$ref": "#/definitions/accountInfo"
            }
          }
        }
      }
    },
    "/bindPhone": {
      "post": {
        "summary": "",
        "operationId": "BindPhone",
        "parameters": [
          {
            "in": "query",
            "name": "phone",
            "type": "string",
            "required": true
          },
          {
            "in": "query",
            "name": "smsCode",
            "type": "string",
            "required": true
          }
        ],
        "security": [
          {
            "Bearer": [
            ]
          }
        ],
        "responses": {
          "200": {
            "description": ""
          }
        }
      }
    },
    "/unbindPhone": {
      "post": {
        "summary": "",
        "operationId": "UnbindPhone",
        "parameters": [
          {
            "in": "query",
            "name": "phone",
            "type": "string",
            "required": true
          },
          {
            "in": "query",
            "name": "smsCode",
            "type": "string",
            "required": true
          }
        ],
        "security": [
          {
            "Bearer": [
            ]
          }
        ],
        "responses": {
          "200": {
            "description": "ok"
          }
        }
      }
    },
    "/bindOauthAccount": {
      "post": {
        "summary": "",
        "operationId": "BindOauthAccount",
        "parameters": [
        ],
        "security": [
          {
            "Bearer": [
            ]
          }
        ],
        "responses": {
          "200": {
            "description": "ok"
          }
        }
      }
    },
    "/unbindOauthAccount": {
      "post": {
        "summary": "",
        "operationId": "UnbindOauthAccount",
        "parameters": [
        ],
        "security": [
          {
            "Bearer": [
            ]
          }
        ],
        "responses": {
          "200": {
            "description": "ok"
          }
        }
      }
    },
    "/operations": {
      "get": {
        "summary": "",
        "operationId": "GetOperationList",
        "parameters": [
          {
            "in": "query",
            "name": "operationType",
            "type": "string"
          },
          {
            "in": "query",
            "name": "pageToken",
            "type": "string"
          },
          {
            "in": "query",
            "name": "pageSize",
            "type": "string",
            "format": "int32"
          }
        ],
        "security": [
          {
            "Bearer": [
            ]
          }
        ],
        "responses": {
          "200": {
            "description": "",
            "schema": {
              "$ref": "#/definitions/operationListResponse"
            }
          }
        }
      }
    }
  },
  "definitions": {
    "smsScene": {
      "type": "string",
      "enum": [
        "SMS_LOGIN",
        "BIND_PHONE",
        "UNBIND_PHONE"
      ]
    },
    "userToken": {
      "type": "object",
      "properties": {
        "accessToken": {
          "type": "string"
        },
        "refreshToken": {
          "type": "string"
        }
      },
      "required": [
        "accessToken",
        "refreshToken"
      ]
    },
    "oauthAccountInfo": {
      "type": "object",
      "properties": {
        "providerID": {
          "type": "string"
        },
        "providerName": {
          "type": "string"
        },
        "openID": {
          "type": "string"
        },
        "userName": {
          "type": "string"
        },
        "userIcon": {
          "type": "string"
        }
      }
    },
    "accountInfo": {
      "type": "object",
      "properties": {
        "userId": {
          "type": "string"
        },
        "userName": {
          "type": "string"
        },
        "userIcon": {
          "type": "string"
        },
        "phoneBinded": {
          "type": "string"
        },
        "oauthBindedList": {
          "type": "array",
          "items": {
            "$ref": "#/definitions/oauthAccountInfo"
          }
        }
      }
    },
    "userInfo": {
      "type": "object",
      "properties": {
        "userId": {
          "type": "string"
        },
        "userName": {
          "type": "string"
        },
        "userIcon": {
          "type": "string"
        }
      }
    },
    "operationType": {
      "type": "string",
      "enum": [
        "SEND_SMS_CODE",
        "SMS_LOGIN",
        "LOGOUT"
      ]
    },
    "operation": {
      "type": "object",
      "properties": {
        "operationId":{
          "type": "string"
        },
        "userId":{
          "type": "string"
        },
        "operationType":{
          "$ref": "#/definitions/operationType"
        },
        "operationTime":{
          "type": "string",
          "format": "date-time"
        },
        "userAgent":{
          "type": "string"
        },
        "phoneMasked":{
          "type": "string"
        },
        "smsScene":{
          "$ref": "#/definitions/smsScene"
        }
      }
    },
    "operationListResponse": {
      "type": "object",
      "properties": {
        "nextPageToken": {
          "type": "string"
        },
        "items": {
          "type": "array",
          "items": {
            "$ref": "#/definitions/operation"
          }
        }
      }
    }
  }
}